[{"parentStoreId":"10061","storeId":10061,"storeNumber":"412","storeDisplayName":"American University Campus Store","langId":"-1","locale":"en_US","currency":"USD","requirementTypeLabelMap":{"RQ":"Required Material(s)","CH":"Choose - Please select from the following...","RM":"Recommended Material(s)","BR":"Suggested by the Bookstore"},"materialTypeKeyList":["TXT","CEB","SUP"],"isViewByLocation":false,"isISBNVisible":true,"isHEOACheckAvailabilityLink":true,"isSuperSite":false,"isEbookStore":true,"isShowRental":true,"isShowNationalRental":false,"isSharedinventory":false,"isCourseTrackStore":true,"isCourseMaterialPreselected":true,"isStoreIncludEDAllStudents":true,"isDigitalFeeEnabledStore":true,"CRNSearchLevel":"NONE","courseLabel":"Course","sectionLabel":"Section","courseSectionDTO":[{"courseSectionStatus":{"status":"FAIL","code":"700","description":"Adoption Status not 500"},"termId":"100071012","termName":"Fall 2021","termNumber":"2021F","termStatus":"A","termOpen":true,"rentalReturnDate":{"year":2021,"month":11,"dayOfMonth":18,"hourOfDay":0,"minute":0,"second":0},"programId":"669","programName":"American University","campusId":"1006","campusName":"American University","institutionName":"American University                                         ","ddcsBreadCrumb":"American University : Fall 2021 : MUS : 021 : 021","adoptionStatus":"100","division":"","divisionName":" ","divisionDescriptorCode":"","department":"MUS","departmentName":"MUS","departmentDescriptorCode":"MUS","course":"021","courseName":"021","courseDescriptorCode":"021","section":"021","sectionName":"021","sectionDescriptorCode":"021","courseId":"80954953","displayFlag":true,"salesTrack":"B","courseMinimum":0,"includEdDTO":{"isStoreIncludEDAllStudents":true,"isIncludEDCampus":false,"isIncludEDSection":false,"isIncludEDTitle":false},"instructor":"Alex Salser","sectionAdoptionDTO":{"courseMaterialRelationship":{},"materialAdoptions":{}},"rentalReturnDateDisplay":"12/18/21"},{"courseSectionStatus":{"status":"FAIL","code":"700","description":"Adoption Status not 500"},"termId":"100071012","termName":"Fall 2021","termNumber":"2021F","termStatus":"A","termOpen":true,"rentalReturnDate":{"year":2021,"month":11,"dayOfMonth":18,"hourOfDay":0,"minute":0,"second":0},"programId":"669","programName":"American University","campusId":"1006","campusName":"American University","institutionName":"American University                                         ","ddcsBreadCrumb":"American University : Fall 2021 : MUS : 021 : 022","adoptionStatus":"100","division":"","divisionName":" ","divisionDescriptorCode":"","department":"MUS","departmentName":"MUS","departmentDescriptorCode":"MUS","course":"021","courseName":"021","courseDescriptorCode":"021","section":"022","sectionName":"022","sectionDescriptorCode":"022","courseId":"80956087","displayFlag":true,"salesTrack":"B","courseMinimum":0,"includEdDTO":{"isStoreIncludEDAllStudents":true,"isIncludEDCampus":false,"isIncludEDSection":false,"isIncludEDTitle":false},"instructor":"Joshua Bayer","sectionAdoptionDTO":{"courseMaterialRelationship":{},"materialAdoptions":{}},"rentalReturnDateDisplay":"12/18/21"},{"courseSectionStatus":{"status":"FAIL","code":"700","description":"Adoption Status not 500"},"termId":"100071012","termName":"Fall 2021","termNumber":"2021F","termStatus":"A","termOpen":true,"rentalReturnDate":{"year":2021,"month":11,"dayOfMonth":18,"hourOfDay":0,"minute":0,"second":0},"programId":"669","programName":"American University","campusId":"1006","campusName":"American University","institutionName":"American University                                         ","ddcsBreadCrumb":"American University : Fall 2021 : MUS : 021 : 023","adoptionStatus":"100","division":"","divisionName":" ","divisionDescriptorCode":"","department":"MUS","departmentName":"MUS","departmentDescriptorCode":"MUS","course":"021","courseName":"021","courseDescriptorCode":"021","section":"023","sectionName":"023","sectionDescriptorCode":"023","courseId":"80965385","displayFlag":true,"salesTrack":"B","courseMinimum":0,"includEdDTO":{"isStoreIncludEDAllStudents":true,"isIncludEDCampus":false,"isIncludEDSection":false,"isIncludEDTitle":false},"instructor":"Alex Salser","sectionAdoptionDTO":{"courseMaterialRelationship":{},"materialAdoptions":{}},"rentalReturnDateDisplay":"12/18/21"},{"courseSectionStatus":{"status":"FAIL","code":"700","description":"Adoption Status not 500"},"termId":"100071012","termName":"Fall 2021","termNumber":"2021F","termStatus":"A","termOpen":true,"rentalReturnDate":{"year":2021,"month":11,"dayOfMonth":18,"hourOfDay":0,"minute":0,"second":0},"programId":"669","programName":"American University","campusId":"1006","campusName":"American University","institutionName":"American University                                         ","ddcsBreadCrumb":"American University : Fall 2021 : MUS : 021 : 024","adoptionStatus":"100","division":"","divisionName":" ","divisionDescriptorCode":"","department":"MUS","departmentName":"MUS","departmentDescriptorCode":"MUS","course":"021","courseName":"021","courseDescriptorCode":"021","section":"024","sectionName":"024","sectionDescriptorCode":"024","courseId":"80954403","displayFlag":true,"salesTrack":"B","courseMinimum":0,"includEdDTO":{"isStoreIncludEDAllStudents":true,"isIncludEDCampus":false,"isIncludEDSection":false,"isIncludEDTitle":false},"instructor":"Joshua Bayer","sectionAdoptionDTO":{"courseMaterialRelationship":{},"materialAdoptions":{}},"rentalReturnDateDisplay":"12/18/21"},{"courseSectionStatus":{"status":"FAIL","code":"700","description":"Adoption Status not 500"},"termId":"100071012","termName":"Fall 2021","termNumber":"2021F","termStatus":"A","termOpen":true,"rentalReturnDate":{"year":2021,"month":11,"dayOfMonth":18,"hourOfDay":0,"minute":0,"second":0},"programId":"669","programName":"American University","campusId":"1006","campusName":"American University","institutionName":"American University                                         ","ddcsBreadCrumb":"American University : Fall 2021 : MUS : 021 : 025","adoptionStatus":"100","division":"","divisionName":" ","divisionDescriptorCode":"","department":"MUS","departmentName":"MUS","departmentDescriptorCode":"MUS","course":"021","courseName":"021","courseDescriptorCode":"021","section":"025","sectionName":"025","sectionDescriptorCode":"025","courseId":"80956711","displayFlag":true,"salesTrack":"B","courseMinimum":0,"includEdDTO":{"isStoreIncludEDAllStudents":true,"isIncludEDCampus":false,"isIncludEDSection":false,"isIncludEDTitle":false},"instructor":"Larry Ferguson","sectionAdoptionDTO":{"courseMaterialRelationship":{},"materialAdoptions":{}},"rentalReturnDateDisplay":"12/18/21"},{"courseSectionStatus":{"status":"FAIL","code":"700","description":"Adoption Status not 500"},"termId":"100071012","termName":"Fall 2021","termNumber":"2021F","termStatus":"A","termOpen":true,"rentalReturnDate":{"year":2021,"month":11,"dayOfMonth":18,"hourOfDay":0,"minute":0,"second":0},"programId":"669","programName":"American University","campusId":"1006","campusName":"American University","institutionName":"American University                                         ","ddcsBreadCrumb":"American University : Fall 2021 : MUS : 021 : 026","adoptionStatus":"100","division":"","divisionName":" ","divisionDescriptorCode":"","department":"MUS","departmentName":"MUS","departmentDescriptorCode":"MUS","course":"021","courseName":"021","courseDescriptorCode":"021","section":"026","sectionName":"026","sectionDescriptorCode":"026","courseId":"80956886","displayFlag":true,"salesTrack":"B","courseMinimum":0,"includEdDTO":{"isStoreIncludEDAllStudents":true,"isIncludEDCampus":false,"isIncludEDSection":false,"isIncludEDTitle":false},"instructor":"Sean Heely","sectionAdoptionDTO":{"courseMaterialRelationship":{},"materialAdoptions":{}},"rentalReturnDateDisplay":"12/18/21"},{"courseSectionStatus":{"status":"FAIL","code":"700","description":"Adoption Status not 500"},"termId":"100071012","termName":"Fall 2021","termNumber":"2021F","termStatus":"A","termOpen":true,"rentalReturnDate":{"year":2021,"month":11,"dayOfMonth":18,"hourOfDay":0,"minute":0,"second":0},"programId":"669","programName":"American University","campusId":"1006","campusName":"American University","institutionName":"American University                                         ","ddcsBreadCrumb":"American University : Fall 2021 : MUS : 021 : 030","adoptionStatus":"100","division":"","divisionName":" ","divisionDescriptorCode":"","department":"MUS","departmentName":"MUS","departmentDescriptorCode":"MUS","course":"021","courseName":"021","courseDescriptorCode":"021","section":"030","sectionName":"030","sectionDescriptorCode":"030","courseId":"80956496","displayFlag":true,"salesTrack":"B","courseMinimum":0,"includEdDTO":{"isStoreIncludEDAllStudents":true,"isIncludEDCampus":false,"isIncludEDSection":false,"isIncludEDTitle":false},"instructor":"Yuliya Gorenman","sectionAdoptionDTO":{"courseMaterialRelationship":{},"materialAdoptions":{}},"rentalReturnDateDisplay":"12/18/21"},{"courseSectionStatus":{"status":"FAIL","code":"700","description":"Adoption Status not 500"},"termId":"100071012","termName":"Fall 2021","termNumber":"2021F","termStatus":"A","termOpen":true,"rentalReturnDate":{"year":2021,"month":11,"dayOfMonth":18,"hourOfDay":0,"minute":0,"second":0},"programId":"669","programName":"American University","campusId":"1006","campusName":"American University","institutionName":"American University                                         ","ddcsBreadCrumb":"American University : Fall 2021 : MUS : 021 : 031","adoptionStatus":"100","division":"","divisionName":" ","divisionDescriptorCode":"","department":"MUS","departmentName":"MUS","departmentDescriptorCode":"MUS","course":"021","courseName":"021","courseDescriptorCode":"021","section":"031","sectionName":"031","sectionDescriptorCode":"031","courseId":"80954187","displayFlag":true,"salesTrack":"B","courseMinimum":0,"includEdDTO":{"isStoreIncludEDAllStudents":true,"isIncludEDCampus":false,"isIncludEDSection":false,"isIncludEDTitle":false},"instructor":"Ann Kang","sectionAdoptionDTO":{"courseMaterialRelationship":{},"materialAdoptions":{}},"rentalReturnDateDisplay":"12/18/21"},{"courseSectionStatus":{"status":"FAIL","code":"700","description":"Adoption Status not 500"},"termId":"100071012","termName":"Fall 2021","termNumber":"2021F","termStatus":"A","termOpen":true,"rentalReturnDate":{"year":2021,"month":11,"dayOfMonth":18,"hourOfDay":0,"minute":0,"second":0},"programId":"669","programName":"American University","campusId":"1006","campusName":"American University","institutionName":"American University                                         ","ddcsBreadCrumb":"American University : Fall 2021 : MUS : 021 : 032","adoptionStatus":"100","division":"","divisionName":" ","divisionDescriptorCode":"","department":"MUS","departmentName":"MUS","departmentDescriptorCode":"MUS","course":"021","courseName":"021","courseDescriptorCode":"021","section":"032","sectionName":"032","sectionDescriptorCode":"032","courseId":"80954247","displayFlag":true,"salesTrack":"B","courseMinimum":0,"includEdDTO":{"isStoreIncludEDAllStudents":true,"isIncludEDCampus":false,"isIncludEDSection":false,"isIncludEDTitle":false},"instructor":"Matthew Van Hoose","sectionAdoptionDTO":{"courseMaterialRelationship":{},"materialAdoptions":{}},"rentalReturnDateDisplay":"12/18/21"},{"courseSectionStatus":{"status":"FAIL","code":"700","description":"Adoption Status not 500"},"termId":"100071012","termName":"Fall 2021","termNumber":"2021F","termStatus":"A","termOpen":true,"rentalReturnDate":{"year":2021,"month":11,"dayOfMonth":18,"hourOfDay":0,"minute":0,"second":0},"programId":"669","programName":"American University","campusId":"1006","campusName":"American University","institutionName":"American University                                         ","ddcsBreadCrumb":"American University : Fall 2021 : MUS : 021 : 033","adoptionStatus":"100","division":"","divisionName":" ","divisionDescriptorCode":"","department":"MUS","departmentName":"MUS","departmentDescriptorCode":"MUS","course":"021","courseName":"021","courseDescriptorCode":"021","section":"033","sectionName":"033","sectionDescriptorCode":"033","courseId":"80965335","displayFlag":true,"salesTrack":"B","courseMinimum":0,"includEdDTO":{"isStoreIncludEDAllStudents":true,"isIncludEDCampus":false,"isIncludEDSection":false,"isIncludEDTitle":false},"instructor":"Jon Ozment","sectionAdoptionDTO":{"courseMaterialRelationship":{},"materialAdoptions":{}},"rentalReturnDateDisplay":"12/18/21"},{"courseSectionStatus":{"status":"FAIL","code":"700","description":"Adoption Status not 500"},"termId":"100071012","termName":"Fall 2021","termNumber":"2021F","termStatus":"A","termOpen":true,"rentalReturnDate":{"year":2021,"month":11,"dayOfMonth":18,"hourOfDay":0,"minute":0,"second":0},"programId":"669","programName":"American University","campusId":"1006","campusName":"American University","institutionName":"American University                                         ","ddcsBreadCrumb":"American University : Fall 2021 : MUS : 021 : 034","adoptionStatus":"100","division":"","divisionName":" ","divisionDescriptorCode":"","department":"MUS","departmentName":"MUS","departmentDescriptorCode":"MUS","course":"021","courseName":"021","courseDescriptorCode":"021","section":"034","sectionName":"034","sectionDescriptorCode":"034","courseId":"80956193","displayFlag":true,"salesTrack":"B","courseMinimum":0,"includEdDTO":{"isStoreIncludEDAllStudents":true,"isIncludEDCampus":false,"isIncludEDSection":false,"isIncludEDTitle":false},"instructor":"Jeffrey Smith","sectionAdoptionDTO":{"courseMaterialRelationship":{},"materialAdoptions":{}},"rentalReturnDateDisplay":"12/18/21"},{"courseSectionStatus":{"status":"FAIL","code":"700","description":"Adoption Status not 500"},"termId":"100071012","termName":"Fall 2021","termNumber":"2021F","termStatus":"A","termOpen":true,"rentalReturnDate":{"year":2021,"month":11,"dayOfMonth":18,"hourOfDay":0,"minute":0,"second":0},"programId":"669","programName":"American University","campusId":"1006","campusName":"American University","institutionName":"American University                                         ","ddcsBreadCrumb":"American University : Fall 2021 : MUS : 021 : 040","adoptionStatus":"100","division":"","divisionName":" ","divisionDescriptorCode":"","department":"MUS","departmentName":"MUS","departmentDescriptorCode":"MUS","course":"021","courseName":"021","courseDescriptorCode":"021","section":"040","sectionName":"040","sectionDescriptorCode":"040","courseId":"80955055","displayFlag":true,"salesTrack":"B","courseMinimum":0,"includEdDTO":{"isStoreIncludEDAllStudents":true,"isIncludEDCampus":false,"isIncludEDSection":false,"isIncludEDTitle":false},"instructor":"Linda Allison","sectionAdoptionDTO":{"courseMaterialRelationship":{},"materialAdoptions":{}},"rentalReturnDateDisplay":"12/18/21"},{"courseSectionStatus":{"status":"FAIL","code":"700","description":"Adoption Status not 500"},"termId":"100071012","termName":"Fall 2021","termNumber":"2021F","termStatus":"A","termOpen":true,"rentalReturnDate":{"year":2021,"month":11,"dayOfMonth":18,"hourOfDay":0,"minute":0,"second":0},"programId":"669","programName":"American University","campusId":"1006","campusName":"American University","institutionName":"American University                                         ","ddcsBreadCrumb":"American University : Fall 2021 : MUS : 021 : 041","adoptionStatus":"100","division":"","divisionName":" ","divisionDescriptorCode":"","department":"MUS","departmentName":"MUS","departmentDescriptorCode":"MUS","course":"021","courseName":"021","courseDescriptorCode":"021","section":"041","sectionName":"041","sectionDescriptorCode":"041","courseId":"80955184","displayFlag":true,"salesTrack":"B","courseMinimum":0,"includEdDTO":{"isStoreIncludEDAllStudents":true,"isIncludEDCampus":false,"isIncludEDSection":false,"isIncludEDTitle":false},"instructor":"Lisa Carrier Baker","sectionAdoptionDTO":{"courseMaterialRelationship":{},"materialAdoptions":{}},"rentalReturnDateDisplay":"12/18/21"},{"courseSectionStatus":{"status":"FAIL","code":"700","description":"Adoption Status not 500"},"termId":"100071012","termName":"Fall 2021","termNumber":"2021F","termStatus":"A","termOpen":true,"rentalReturnDate":{"year":2021,"month":11,"dayOfMonth":18,"hourOfDay":0,"minute":0,"second":0},"programId":"669","programName":"American University","campusId":"1006","campusName":"American University","institutionName":"American University                                         ","ddcsBreadCrumb":"American University : Fall 2021 : MUS : 021 : 042","adoptionStatus":"100","division":"","divisionName":" ","divisionDescriptorCode":"","department":"MUS","departmentName":"MUS","departmentDescriptorCode":"MUS","course":"021","courseName":"021","courseDescriptorCode":"021","section":"042","sectionName":"042","sectionDescriptorCode":"042","courseId":"80955227","displayFlag":true,"salesTrack":"B","courseMinimum":0,"includEdDTO":{"isStoreIncludEDAllStudents":true,"isIncludEDCampus":false,"isIncludEDSection":false,"isIncludEDTitle":false},"instructor":"Susan Derry","sectionAdoptionDTO":{"courseMaterialRelationship":{},"materialAdoptions":{}},"rentalReturnDateDisplay":"12/18/21"},{"courseSectionStatus":{"status":"FAIL","code":"700","description":"Adoption Status not 500"},"termId":"100071012","termName":"Fall 2021","termNumber":"2021F","termStatus":"A","termOpen":true,"rentalReturnDate":{"year":2021,"month":11,"dayOfMonth":18,"hourOfDay":0,"minute":0,"second":0},"programId":"669","programName":"American University","campusId":"1006","campusName":"American University","institutionName":"American University                                         ","ddcsBreadCrumb":"American University : Fall 2021 : MUS : 021 : 043","adoptionStatus":"100","division":"","divisionName":" ","divisionDescriptorCode":"","department":"MUS","departmentName":"MUS","departmentDescriptorCode":"MUS","course":"021","courseName":"021","courseDescriptorCode":"021","section":"043","sectionName":"043","sectionDescriptorCode":"043","courseId":"80954982","displayFlag":true,"salesTrack":"B","courseMinimum":0,"includEdDTO":{"isStoreIncludEDAllStudents":true,"isIncludEDCampus":false,"isIncludEDSection":false,"isIncludEDTitle":false},"instructor":"Barbara Hollinshead","sectionAdoptionDTO":{"courseMaterialRelationship":{},"materialAdoptions":{}},"rentalReturnDateDisplay":"12/18/21"},{"courseSectionStatus":{"status":"FAIL","code":"700","description":"Adoption Status not 500"},"termId":"100071012","termName":"Fall 2021","termNumber":"2021F","termStatus":"A","termOpen":true,"rentalReturnDate":{"year":2021,"month":11,"dayOfMonth":18,"hourOfDay":0,"minute":0,"second":0},"programId":"669","programName":"American University","campusId":"1006","campusName":"American University","institutionName":"American University                                         ","ddcsBreadCrumb":"American University : Fall 2021 : MUS : 021 : 044","adoptionStatus":"100","division":"","divisionName":" ","divisionDescriptorCode":"","department":"MUS","departmentName":"MUS","departmentDescriptorCode":"MUS","course":"021","courseName":"021","courseDescriptorCode":"021","section":"044","sectionName":"044","sectionDescriptorCode":"044","courseId":"80954143","displayFlag":true,"salesTrack":"B","courseMinimum":0,"includEdDTO":{"isStoreIncludEDAllStudents":true,"isIncludEDCampus":false,"isIncludEDSection":false,"isIncludEDTitle":false},"instructor":"Katherine Riddle","sectionAdoptionDTO":{"courseMaterialRelationship":{},"materialAdoptions":{}},"rentalReturnDateDisplay":"12/18/21"},{"courseSectionStatus":{"status":"FAIL","code":"700","description":"Adoption Status not 500"},"termId":"100071012","termName":"Fall 2021","termNumber":"2021F","termStatus":"A","termOpen":true,"rentalReturnDate":{"year":2021,"month":11,"dayOfMonth":18,"hourOfDay":0,"minute":0,"second":0},"programId":"669","programName":"American University","campusId":"1006","campusName":"American University","institutionName":"American University                                         ","ddcsBreadCrumb":"American University : Fall 2021 : MUS : 021 : 045","adoptionStatus":"100","division":"","divisionName":" ","divisionDescriptorCode":"","department":"MUS","departmentName":"MUS","departmentDescriptorCode":"MUS","course":"021","courseName":"021","courseDescriptorCode":"021","section":"045","sectionName":"045","sectionDescriptorCode":"045","courseId":"80954445","displayFlag":true,"salesTrack":"B","courseMinimum":0,"includEdDTO":{"isStoreIncludEDAllStudents":true,"isIncludEDCampus":false,"isIncludEDSection":false,"isIncludEDTitle":false},"instructor":"Sterling Scroggins","sectionAdoptionDTO":{"courseMaterialRelationship":{},"materialAdoptions":{}},"rentalReturnDateDisplay":"12/18/21"},{"courseSectionStatus":{"status":"FAIL","code":"700","description":"Adoption Status not 500"},"termId":"100071012","termName":"Fall 2021","termNumber":"2021F","termStatus":"A","termOpen":true,"rentalReturnDate":{"year":2021,"month":11,"dayOfMonth":18,"hourOfDay":0,"minute":0,"second":0},"programId":"669","programName":"American University","campusId":"1006","campusName":"American University","institutionName":"American University                                         ","ddcsBreadCrumb":"American University : Fall 2021 : MUS : 021 : 046","adoptionStatus":"100","division":"","divisionName":" ","divisionDescriptorCode":"","department":"MUS","departmentName":"MUS","departmentDescriptorCode":"MUS","course":"021","courseName":"021","courseDescriptorCode":"021","section":"046","sectionName":"046","sectionDescriptorCode":"046","courseId":"80954952","displayFlag":true,"salesTrack":"B","courseMinimum":0,"includEdDTO":{"isStoreIncludEDAllStudents":true,"isIncludEDCampus":false,"isIncludEDSection":false,"isIncludEDTitle":false},"instructor":"Kelly Smith Jones","sectionAdoptionDTO":{"courseMaterialRelationship":{},"materialAdoptions":{}},"rentalReturnDateDisplay":"12/18/21"},{"courseSectionStatus":{"status":"FAIL","code":"700","description":"Adoption Status not 500"},"termId":"100071012","termName":"Fall 2021","termNumber":"2021F","termStatus":"A","termOpen":true,"rentalReturnDate":{"year":2021,"month":11,"dayOfMonth":18,"hourOfDay":0,"minute":0,"second":0},"programId":"669","programName":"American University","campusId":"1006","campusName":"American University","institutionName":"American University                                         ","ddcsBreadCrumb":"American University : Fall 2021 : MUS : 021 : 047","adoptionStatus":"100","division":"","divisionName":" ","divisionDescriptorCode":"","department":"MUS","departmentName":"MUS","departmentDescriptorCode":"MUS","course":"021","courseName":"021","courseDescriptorCode":"021","section":"047","sectionName":"047","sectionDescriptorCode":"047","courseId":"80955457","displayFlag":true,"salesTrack":"B","courseMinimum":0,"includEdDTO":{"isStoreIncludEDAllStudents":true,"isIncludEDCampus":false,"isIncludEDSection":false,"isIncludEDTitle":false},"instructor":"Ethan Watermeier","sectionAdoptionDTO":{"courseMaterialRelationship":{},"materialAdoptions":{}},"rentalReturnDateDisplay":"12/18/21"},{"courseSectionStatus":{"status":"FAIL","code":"700","description":"Adoption Status not 500"},"termId":"100071012","termName":"Fall 2021","termNumber":"2021F","termStatus":"A","termOpen":true,"rentalReturnDate":{"year":2021,"month":11,"dayOfMonth":18,"hourOfDay":0,"minute":0,"second":0},"programId":"669","programName":"American University","campusId":"1006","campusName":"American University","institutionName":"American University                                         ","ddcsBreadCrumb":"American University : Fall 2021 : MUS : 021 : 048","adoptionStatus":"100","division":"","divisionName":" ","divisionDescriptorCode":"","department":"MUS","departmentName":"MUS","departmentDescriptorCode":"MUS","course":"021","courseName":"021","courseDescriptorCode":"021","section":"048","sectionName":"048","sectionDescriptorCode":"048","courseId":"80954628","displayFlag":true,"salesTrack":"B","courseMinimum":0,"includEdDTO":{"isStoreIncludEDAllStudents":true,"isIncludEDCampus":false,"isIncludEDSection":false,"isIncludEDTitle":false},"instructor":"Mark Meadows","sectionAdoptionDTO":{"courseMaterialRelationship":{},"materialAdoptions":{}},"rentalReturnDateDisplay":"12/18/21"}],"statusDTO":{"status":"SUCCESS","code":"0"},"homePageURL":"/Home/11077-10061-1?demoKey=d","searchLimit":0,"DDCSBrowseRetentionLevel":"TERM","accordionControl":"ALL_CLOSED","ddcsNotesControl":"NOTES_CLOSED","digitalSurChargeFee":"3.99","summaryProfile":false}]