[{"parentStoreId":"10061","storeId":10061,"storeNumber":"412","storeDisplayName":"American University Campus Store","langId":"-1","locale":"en_US","currency":"USD","requirementTypeLabelMap":{"RQ":"Required Material(s)","CH":"Choose - Please select from the following...","RM":"Recommended Material(s)","BR":"Suggested by the Bookstore"},"materialTypeKeyList":["TXT","CEB","SUP"],"isViewByLocation":false,"isISBNVisible":true,"isHEOACheckAvailabilityLink":true,"isSuperSite":false,"isEbookStore":true,"isShowRental":true,"isShowNationalRental":false,"isSharedinventory":false,"isCourseTrackStore":true,"isCourseMaterialPreselected":true,"isStoreIncludEDAllStudents":true,"isDigitalFeeEnabledStore":true,"CRNSearchLevel":"NONE","courseLabel":"Course","sectionLabel":"Section","courseSectionDTO":[{"courseSectionStatus":{"status":"FAIL","code":"700","description":"Adoption Status not 500"},"termId":"100071012","termName":"Fall 2021","termNumber":"2021F","termStatus":"A","termOpen":true,"rentalReturnDate":{"year":2021,"month":11,"dayOfMonth":18,"hourOfDay":0,"minute":0,"second":0},"programId":"669","programName":"American University","campusId":"1006","campusName":"American University","institutionName":"American University                                         ","ddcsBreadCrumb":"American University : Fall 2021 : SPEX : 070 : 001","adoptionStatus":"100","division":"","divisionName":" ","divisionDescriptorCode":"","department":"SPEX","departmentName":"SPEX","departmentDescriptorCode":"SPEX","course":"070","courseName":"070","courseDescriptorCode":"070","section":"001","sectionName":"001","sectionDescriptorCode":"001","courseId":"81966821","displayFlag":true,"salesTrack":"B","courseMinimum":0,"includEdDTO":{"isStoreIncludEDAllStudents":true,"isIncludEDCampus":false,"isIncludEDSection":false,"isIncludEDTitle":false},"instructor":"Eric Blount","sectionAdoptionDTO":{"courseMaterialRelationship":{},"materialAdoptions":{}},"rentalReturnDateDisplay":"12/18/21"},{"courseSectionStatus":{"status":"FAIL","code":"700","description":"Adoption Status not 500"},"termId":"100071012","termName":"Fall 2021","termNumber":"2021F","termStatus":"A","termOpen":true,"rentalReturnDate":{"year":2021,"month":11,"dayOfMonth":18,"hourOfDay":0,"minute":0,"second":0},"programId":"669","programName":"American University","campusId":"1006","campusName":"American University","institutionName":"American University                                         ","ddcsBreadCrumb":"American University : Fall 2021 : SPEX : 070 : 002","adoptionStatus":"100","division":"","divisionName":" ","divisionDescriptorCode":"","department":"SPEX","departmentName":"SPEX","departmentDescriptorCode":"SPEX","course":"070","courseName":"070","courseDescriptorCode":"070","section":"002","sectionName":"002","sectionDescriptorCode":"002","courseId":"81966830","displayFlag":true,"salesTrack":"B","courseMinimum":0,"includEdDTO":{"isStoreIncludEDAllStudents":true,"isIncludEDCampus":false,"isIncludEDSection":false,"isIncludEDTitle":false},"instructor":"Eric Blount","sectionAdoptionDTO":{"courseMaterialRelationship":{},"materialAdoptions":{}},"rentalReturnDateDisplay":"12/18/21"},{"courseSectionStatus":{"status":"FAIL","code":"700","description":"Adoption Status not 500"},"termId":"100071012","termName":"Fall 2021","termNumber":"2021F","termStatus":"A","termOpen":true,"rentalReturnDate":{"year":2021,"month":11,"dayOfMonth":18,"hourOfDay":0,"minute":0,"second":0},"programId":"669","programName":"American University","campusId":"1006","campusName":"American University","institutionName":"American University                                         ","ddcsBreadCrumb":"American University : Fall 2021 : SPEX : 070 : 003","adoptionStatus":"100","division":"","divisionName":" ","divisionDescriptorCode":"","department":"SPEX","departmentName":"SPEX","departmentDescriptorCode":"SPEX","course":"070","courseName":"070","courseDescriptorCode":"070","section":"003","sectionName":"003","sectionDescriptorCode":"003","courseId":"81966857","displayFlag":true,"salesTrack":"B","courseMinimum":0,"includEdDTO":{"isStoreIncludEDAllStudents":true,"isIncludEDCampus":false,"isIncludEDSection":false,"isIncludEDTitle":false},"instructor":"Eric Blount","sectionAdoptionDTO":{"courseMaterialRelationship":{},"materialAdoptions":{}},"rentalReturnDateDisplay":"12/18/21"},{"courseSectionStatus":{"status":"FAIL","code":"700","description":"Adoption Status not 500"},"termId":"100071012","termName":"Fall 2021","termNumber":"2021F","termStatus":"A","termOpen":true,"rentalReturnDate":{"year":2021,"month":11,"dayOfMonth":18,"hourOfDay":0,"minute":0,"second":0},"programId":"669","programName":"American University","campusId":"1006","campusName":"American University","institutionName":"American University                                         ","ddcsBreadCrumb":"American University : Fall 2021 : SPEX : 070 : 004","adoptionStatus":"100","division":"","divisionName":" ","divisionDescriptorCode":"","department":"SPEX","departmentName":"SPEX","departmentDescriptorCode":"SPEX","course":"070","courseName":"070","courseDescriptorCode":"070","section":"004","sectionName":"004","sectionDescriptorCode":"004","courseId":"81966844","displayFlag":true,"salesTrack":"B","courseMinimum":0,"includEdDTO":{"isStoreIncludEDAllStudents":true,"isIncludEDCampus":false,"isIncludEDSection":false,"isIncludEDTitle":false},"instructor":"Eric Blount","sectionAdoptionDTO":{"courseMaterialRelationship":{},"materialAdoptions":{}},"rentalReturnDateDisplay":"12/18/21"},{"courseSectionStatus":{"status":"FAIL","code":"700","description":"Adoption Status not 500"},"termId":"100071012","termName":"Fall 2021","termNumber":"2021F","termStatus":"A","termOpen":true,"rentalReturnDate":{"year":2021,"month":11,"dayOfMonth":18,"hourOfDay":0,"minute":0,"second":0},"programId":"669","programName":"American University","campusId":"1006","campusName":"American University","institutionName":"American University                                         ","ddcsBreadCrumb":"American University : Fall 2021 : SPEX : 070 : 005","adoptionStatus":"100","division":"","divisionName":" ","divisionDescriptorCode":"","department":"SPEX","departmentName":"SPEX","departmentDescriptorCode":"SPEX","course":"070","courseName":"070","courseDescriptorCode":"070","section":"005","sectionName":"005","sectionDescriptorCode":"005","courseId":"81966863","displayFlag":true,"salesTrack":"B","courseMinimum":0,"includEdDTO":{"isStoreIncludEDAllStudents":true,"isIncludEDCampus":false,"isIncludEDSection":false,"isIncludEDTitle":false},"instructor":"Eric Blount","sectionAdoptionDTO":{"courseMaterialRelationship":{},"materialAdoptions":{}},"rentalReturnDateDisplay":"12/18/21"},{"courseSectionStatus":{"status":"FAIL","code":"700","description":"Adoption Status not 500"},"termId":"100071012","termName":"Fall 2021","termNumber":"2021F","termStatus":"A","termOpen":true,"rentalReturnDate":{"year":2021,"month":11,"dayOfMonth":18,"hourOfDay":0,"minute":0,"second":0},"programId":"669","programName":"American University","campusId":"1006","campusName":"American University","institutionName":"American University                                         ","ddcsBreadCrumb":"American University : Fall 2021 : SPEX : 070 : 006","adoptionStatus":"100","division":"","divisionName":" ","divisionDescriptorCode":"","department":"SPEX","departmentName":"SPEX","departmentDescriptorCode":"SPEX","course":"070","courseName":"070","courseDescriptorCode":"070","section":"006","sectionName":"006","sectionDescriptorCode":"006","courseId":"81966815","displayFlag":true,"salesTrack":"B","courseMinimum":0,"includEdDTO":{"isStoreIncludEDAllStudents":true,"isIncludEDCampus":false,"isIncludEDSection":false,"isIncludEDTitle":false},"instructor":"Eric Blount","sectionAdoptionDTO":{"courseMaterialRelationship":{},"materialAdoptions":{}},"rentalReturnDateDisplay":"12/18/21"},{"courseSectionStatus":{"status":"FAIL","code":"700","description":"Adoption Status not 500"},"termId":"100071012","termName":"Fall 2021","termNumber":"2021F","termStatus":"A","termOpen":true,"rentalReturnDate":{"year":2021,"month":11,"dayOfMonth":18,"hourOfDay":0,"minute":0,"second":0},"programId":"669","programName":"American University","campusId":"1006","campusName":"American University","institutionName":"American University                                         ","ddcsBreadCrumb":"American University : Fall 2021 : SPEX : 070 : 007","adoptionStatus":"100","division":"","divisionName":" ","divisionDescriptorCode":"","department":"SPEX","departmentName":"SPEX","departmentDescriptorCode":"SPEX","course":"070","courseName":"070","courseDescriptorCode":"070","section":"007","sectionName":"007","sectionDescriptorCode":"007","courseId":"81966924","displayFlag":true,"salesTrack":"B","courseMinimum":0,"includEdDTO":{"isStoreIncludEDAllStudents":true,"isIncludEDCampus":false,"isIncludEDSection":false,"isIncludEDTitle":false},"instructor":"Eric Blount","sectionAdoptionDTO":{"courseMaterialRelationship":{},"materialAdoptions":{}},"rentalReturnDateDisplay":"12/18/21"},{"courseSectionStatus":{"status":"FAIL","code":"700","description":"Adoption Status not 500"},"termId":"100071012","termName":"Fall 2021","termNumber":"2021F","termStatus":"A","termOpen":true,"rentalReturnDate":{"year":2021,"month":11,"dayOfMonth":18,"hourOfDay":0,"minute":0,"second":0},"programId":"669","programName":"American University","campusId":"1006","campusName":"American University","institutionName":"American University                                         ","ddcsBreadCrumb":"American University : Fall 2021 : SPEX : 070 : 008","adoptionStatus":"100","division":"","divisionName":" ","divisionDescriptorCode":"","department":"SPEX","departmentName":"SPEX","departmentDescriptorCode":"SPEX","course":"070","courseName":"070","courseDescriptorCode":"070","section":"008","sectionName":"008","sectionDescriptorCode":"008","courseId":"81966818","displayFlag":true,"salesTrack":"B","courseMinimum":0,"includEdDTO":{"isStoreIncludEDAllStudents":true,"isIncludEDCampus":false,"isIncludEDSection":false,"isIncludEDTitle":false},"instructor":"Eric Blount","sectionAdoptionDTO":{"courseMaterialRelationship":{},"materialAdoptions":{}},"rentalReturnDateDisplay":"12/18/21"},{"courseSectionStatus":{"status":"FAIL","code":"700","description":"Adoption Status not 500"},"termId":"100071012","termName":"Fall 2021","termNumber":"2021F","termStatus":"A","termOpen":true,"rentalReturnDate":{"year":2021,"month":11,"dayOfMonth":18,"hourOfDay":0,"minute":0,"second":0},"programId":"669","programName":"American University","campusId":"1006","campusName":"American University","institutionName":"American University                                         ","ddcsBreadCrumb":"American University : Fall 2021 : SPEX : 071 : 001","adoptionStatus":"100","division":"","divisionName":" ","divisionDescriptorCode":"","department":"SPEX","departmentName":"SPEX","departmentDescriptorCode":"SPEX","course":"071","courseName":"071","courseDescriptorCode":"071","section":"001","sectionName":"001","sectionDescriptorCode":"001","courseId":"81966856","displayFlag":true,"salesTrack":"B","courseMinimum":0,"includEdDTO":{"isStoreIncludEDAllStudents":true,"isIncludEDCampus":false,"isIncludEDSection":false,"isIncludEDTitle":false},"instructor":"Eric Blount","sectionAdoptionDTO":{"courseMaterialRelationship":{},"materialAdoptions":{}},"rentalReturnDateDisplay":"12/18/21"},{"courseSectionStatus":{"status":"FAIL","code":"700","description":"Adoption Status not 500"},"termId":"100071012","termName":"Fall 2021","termNumber":"2021F","termStatus":"A","termOpen":true,"rentalReturnDate":{"year":2021,"month":11,"dayOfMonth":18,"hourOfDay":0,"minute":0,"second":0},"programId":"669","programName":"American University","campusId":"1006","campusName":"American University","institutionName":"American University                                         ","ddcsBreadCrumb":"American University : Fall 2021 : SPEX : 071 : 002","adoptionStatus":"100","division":"","divisionName":" ","divisionDescriptorCode":"","department":"SPEX","departmentName":"SPEX","departmentDescriptorCode":"SPEX","course":"071","courseName":"071","courseDescriptorCode":"071","section":"002","sectionName":"002","sectionDescriptorCode":"002","courseId":"81966800","displayFlag":true,"salesTrack":"B","courseMinimum":0,"includEdDTO":{"isStoreIncludEDAllStudents":true,"isIncludEDCampus":false,"isIncludEDSection":false,"isIncludEDTitle":false},"instructor":"Eric Blount","sectionAdoptionDTO":{"courseMaterialRelationship":{},"materialAdoptions":{}},"rentalReturnDateDisplay":"12/18/21"},{"courseSectionStatus":{"status":"FAIL","code":"700","description":"Adoption Status not 500"},"termId":"100071012","termName":"Fall 2021","termNumber":"2021F","termStatus":"A","termOpen":true,"rentalReturnDate":{"year":2021,"month":11,"dayOfMonth":18,"hourOfDay":0,"minute":0,"second":0},"programId":"669","programName":"American University","campusId":"1006","campusName":"American University","institutionName":"American University                                         ","ddcsBreadCrumb":"American University : Fall 2021 : SPEX : 074 : 001","adoptionStatus":"100","division":"","divisionName":" ","divisionDescriptorCode":"","department":"SPEX","departmentName":"SPEX","departmentDescriptorCode":"SPEX","course":"074","courseName":"074","courseDescriptorCode":"074","section":"001","sectionName":"001","sectionDescriptorCode":"001","courseId":"81967070","displayFlag":true,"salesTrack":"B","courseMinimum":0,"includEdDTO":{"isStoreIncludEDAllStudents":true,"isIncludEDCampus":false,"isIncludEDSection":false,"isIncludEDTitle":false},"instructor":"","sectionAdoptionDTO":{"courseMaterialRelationship":{},"materialAdoptions":{}},"rentalReturnDateDisplay":"12/18/21"},{"courseSectionStatus":{"status":"FAIL","code":"700","description":"Adoption Status not 500"},"termId":"100071012","termName":"Fall 2021","termNumber":"2021F","termStatus":"A","termOpen":true,"rentalReturnDate":{"year":2021,"month":11,"dayOfMonth":18,"hourOfDay":0,"minute":0,"second":0},"programId":"669","programName":"American University","campusId":"1006","campusName":"American University","institutionName":"American University                                         ","ddcsBreadCrumb":"American University : Fall 2021 : SPEX : 074 : 002","adoptionStatus":"100","division":"","divisionName":" ","divisionDescriptorCode":"","department":"SPEX","departmentName":"SPEX","departmentDescriptorCode":"SPEX","course":"074","courseName":"074","courseDescriptorCode":"074","section":"002","sectionName":"002","sectionDescriptorCode":"002","courseId":"81967069","displayFlag":true,"salesTrack":"B","courseMinimum":0,"includEdDTO":{"isStoreIncludEDAllStudents":true,"isIncludEDCampus":false,"isIncludEDSection":false,"isIncludEDTitle":false},"instructor":"","sectionAdoptionDTO":{"courseMaterialRelationship":{},"materialAdoptions":{}},"rentalReturnDateDisplay":"12/18/21"},{"courseSectionStatus":{"status":"FAIL","code":"700","description":"Adoption Status not 500"},"termId":"100071012","termName":"Fall 2021","termNumber":"2021F","termStatus":"A","termOpen":true,"rentalReturnDate":{"year":2021,"month":11,"dayOfMonth":18,"hourOfDay":0,"minute":0,"second":0},"programId":"669","programName":"American University","campusId":"1006","campusName":"American University","institutionName":"American University                                         ","ddcsBreadCrumb":"American University : Fall 2021 : SPEX : 074 : 003","adoptionStatus":"100","division":"","divisionName":" ","divisionDescriptorCode":"","department":"SPEX","departmentName":"SPEX","departmentDescriptorCode":"SPEX","course":"074","courseName":"074","courseDescriptorCode":"074","section":"003","sectionName":"003","sectionDescriptorCode":"003","courseId":"82132639","displayFlag":true,"salesTrack":"B","courseMinimum":0,"includEdDTO":{"isStoreIncludEDAllStudents":true,"isIncludEDCampus":false,"isIncludEDSection":false,"isIncludEDTitle":false},"instructor":"","sectionAdoptionDTO":{"courseMaterialRelationship":{},"materialAdoptions":{}},"rentalReturnDateDisplay":"12/18/21"},{"courseSectionStatus":{"status":"FAIL","code":"700","description":"Adoption Status not 500"},"termId":"100071012","termName":"Fall 2021","termNumber":"2021F","termStatus":"A","termOpen":true,"rentalReturnDate":{"year":2021,"month":11,"dayOfMonth":18,"hourOfDay":0,"minute":0,"second":0},"programId":"669","programName":"American University","campusId":"1006","campusName":"American University","institutionName":"American University                                         ","ddcsBreadCrumb":"American University : Fall 2021 : SPEX : 074 : 004","adoptionStatus":"100","division":"","divisionName":" ","divisionDescriptorCode":"","department":"SPEX","departmentName":"SPEX","departmentDescriptorCode":"SPEX","course":"074","courseName":"074","courseDescriptorCode":"074","section":"004","sectionName":"004","sectionDescriptorCode":"004","courseId":"82132619","displayFlag":true,"salesTrack":"B","courseMinimum":0,"includEdDTO":{"isStoreIncludEDAllStudents":true,"isIncludEDCampus":false,"isIncludEDSection":false,"isIncludEDTitle":false},"instructor":"","sectionAdoptionDTO":{"courseMaterialRelationship":{},"materialAdoptions":{}},"rentalReturnDateDisplay":"12/18/21"},{"courseSectionStatus":{"status":"FAIL","code":"700","description":"Adoption Status not 500"},"termId":"100071012","termName":"Fall 2021","termNumber":"2021F","termStatus":"A","termOpen":true,"rentalReturnDate":{"year":2021,"month":11,"dayOfMonth":18,"hourOfDay":0,"minute":0,"second":0},"programId":"669","programName":"American University","campusId":"1006","campusName":"American University","institutionName":"American University                                         ","ddcsBreadCrumb":"American University : Fall 2021 : SPEX : 075 : 001","adoptionStatus":"100","division":"","divisionName":" ","divisionDescriptorCode":"","department":"SPEX","departmentName":"SPEX","departmentDescriptorCode":"SPEX","course":"075","courseName":"075","courseDescriptorCode":"075","section":"001","sectionName":"001","sectionDescriptorCode":"001","courseId":"81967042","displayFlag":true,"salesTrack":"B","courseMinimum":0,"includEdDTO":{"isStoreIncludEDAllStudents":true,"isIncludEDCampus":false,"isIncludEDSection":false,"isIncludEDTitle":false},"instructor":"","sectionAdoptionDTO":{"courseMaterialRelationship":{},"materialAdoptions":{}},"rentalReturnDateDisplay":"12/18/21"},{"courseSectionStatus":{"status":"FAIL","code":"700","description":"Adoption Status not 500"},"termId":"100071012","termName":"Fall 2021","termNumber":"2021F","termStatus":"A","termOpen":true,"rentalReturnDate":{"year":2021,"month":11,"dayOfMonth":18,"hourOfDay":0,"minute":0,"second":0},"programId":"669","programName":"American University","campusId":"1006","campusName":"American University","institutionName":"American University                                         ","ddcsBreadCrumb":"American University : Fall 2021 : SPEX : 075 : 002","adoptionStatus":"100","division":"","divisionName":" ","divisionDescriptorCode":"","department":"SPEX","departmentName":"SPEX","departmentDescriptorCode":"SPEX","course":"075","courseName":"075","courseDescriptorCode":"075","section":"002","sectionName":"002","sectionDescriptorCode":"002","courseId":"82132657","displayFlag":true,"salesTrack":"B","courseMinimum":0,"includEdDTO":{"isStoreIncludEDAllStudents":true,"isIncludEDCampus":false,"isIncludEDSection":false,"isIncludEDTitle":false},"instructor":"","sectionAdoptionDTO":{"courseMaterialRelationship":{},"materialAdoptions":{}},"rentalReturnDateDisplay":"12/18/21"},{"courseSectionStatus":{"status":"FAIL","code":"700","description":"Adoption Status not 500"},"termId":"100071012","termName":"Fall 2021","termNumber":"2021F","termStatus":"A","termOpen":true,"rentalReturnDate":{"year":2021,"month":11,"dayOfMonth":18,"hourOfDay":0,"minute":0,"second":0},"programId":"669","programName":"American University","campusId":"1006","campusName":"American University","institutionName":"American University                                         ","ddcsBreadCrumb":"American University : Fall 2021 : SPEX : 076 : 001","adoptionStatus":"100","division":"","divisionName":" ","divisionDescriptorCode":"","department":"SPEX","departmentName":"SPEX","departmentDescriptorCode":"SPEX","course":"076","courseName":"076","courseDescriptorCode":"076","section":"001","sectionName":"001","sectionDescriptorCode":"001","courseId":"82132698","displayFlag":true,"salesTrack":"B","courseMinimum":0,"includEdDTO":{"isStoreIncludEDAllStudents":true,"isIncludEDCampus":false,"isIncludEDSection":false,"isIncludEDTitle":false},"instructor":"","sectionAdoptionDTO":{"courseMaterialRelationship":{},"materialAdoptions":{}},"rentalReturnDateDisplay":"12/18/21"},{"courseSectionStatus":{"status":"FAIL","code":"700","description":"Adoption Status not 500"},"termId":"100071012","termName":"Fall 2021","termNumber":"2021F","termStatus":"A","termOpen":true,"rentalReturnDate":{"year":2021,"month":11,"dayOfMonth":18,"hourOfDay":0,"minute":0,"second":0},"programId":"669","programName":"American University","campusId":"1006","campusName":"American University","institutionName":"American University                                         ","ddcsBreadCrumb":"American University : Fall 2021 : SPEX : 076 : 002","adoptionStatus":"100","division":"","divisionName":" ","divisionDescriptorCode":"","department":"SPEX","departmentName":"SPEX","departmentDescriptorCode":"SPEX","course":"076","courseName":"076","courseDescriptorCode":"076","section":"002","sectionName":"002","sectionDescriptorCode":"002","courseId":"82132696","displayFlag":true,"salesTrack":"B","courseMinimum":0,"includEdDTO":{"isStoreIncludEDAllStudents":true,"isIncludEDCampus":false,"isIncludEDSection":false,"isIncludEDTitle":false},"instructor":"","sectionAdoptionDTO":{"courseMaterialRelationship":{},"materialAdoptions":{}},"rentalReturnDateDisplay":"12/18/21"},{"courseSectionStatus":{"status":"FAIL","code":"700","description":"Adoption Status not 500"},"termId":"100071012","termName":"Fall 2021","termNumber":"2021F","termStatus":"A","termOpen":true,"rentalReturnDate":{"year":2021,"month":11,"dayOfMonth":18,"hourOfDay":0,"minute":0,"second":0},"programId":"669","programName":"American University","campusId":"1006","campusName":"American University","institutionName":"American University                                         ","ddcsBreadCrumb":"American University : Fall 2021 : SPEX : 077 : 001","adoptionStatus":"100","division":"","divisionName":" ","divisionDescriptorCode":"","department":"SPEX","departmentName":"SPEX","departmentDescriptorCode":"SPEX","course":"077","courseName":"077","courseDescriptorCode":"077","section":"001","sectionName":"001","sectionDescriptorCode":"001","courseId":"82132697","displayFlag":true,"salesTrack":"B","courseMinimum":0,"includEdDTO":{"isStoreIncludEDAllStudents":true,"isIncludEDCampus":false,"isIncludEDSection":false,"isIncludEDTitle":false},"instructor":"","sectionAdoptionDTO":{"courseMaterialRelationship":{},"materialAdoptions":{}},"rentalReturnDateDisplay":"12/18/21"},{"courseSectionStatus":{"status":"FAIL","code":"700","description":"Adoption Status not 500"},"termId":"100071012","termName":"Fall 2021","termNumber":"2021F","termStatus":"A","termOpen":true,"rentalReturnDate":{"year":2021,"month":11,"dayOfMonth":18,"hourOfDay":0,"minute":0,"second":0},"programId":"669","programName":"American University","campusId":"1006","campusName":"American University","institutionName":"American University                                         ","ddcsBreadCrumb":"American University : Fall 2021 : SPEX : 080 : 001","adoptionStatus":"100","division":"","divisionName":" ","divisionDescriptorCode":"","department":"SPEX","departmentName":"SPEX","departmentDescriptorCode":"SPEX","course":"080","courseName":"080","courseDescriptorCode":"080","section":"001","sectionName":"001","sectionDescriptorCode":"001","courseId":"81468279","displayFlag":true,"salesTrack":"B","courseMinimum":0,"includEdDTO":{"isStoreIncludEDAllStudents":true,"isIncludEDCampus":false,"isIncludEDSection":false,"isIncludEDTitle":false},"instructor":"Christopher Brookfield","sectionAdoptionDTO":{"courseMaterialRelationship":{},"materialAdoptions":{}},"rentalReturnDateDisplay":"12/18/21"}],"statusDTO":{"status":"SUCCESS","code":"0"},"homePageURL":"/Home/11077-10061-1?demoKey=d","searchLimit":0,"DDCSBrowseRetentionLevel":"TERM","accordionControl":"ALL_CLOSED","ddcsNotesControl":"NOTES_CLOSED","digitalSurChargeFee":"3.99","summaryProfile":false}]