[{"parentStoreId":"10061","storeId":10061,"storeNumber":"412","storeDisplayName":"American University Campus Store","langId":"-1","locale":"en_US","currency":"USD","requirementTypeLabelMap":{"RQ":"Required Material(s)","CH":"Choose - Please select from the following...","RM":"Recommended Material(s)","BR":"Suggested by the Bookstore"},"materialTypeKeyList":["TXT","CEB","SUP"],"isViewByLocation":false,"isISBNVisible":true,"isHEOACheckAvailabilityLink":true,"isSuperSite":false,"isEbookStore":true,"isShowRental":true,"isShowNationalRental":false,"isSharedinventory":false,"isCourseTrackStore":true,"isCourseMaterialPreselected":true,"isStoreIncludEDAllStudents":true,"isDigitalFeeEnabledStore":true,"CRNSearchLevel":"NONE","courseLabel":"Course","sectionLabel":"Section","courseSectionDTO":[{"courseSectionStatus":{"status":"FAIL","code":"700","description":"Adoption Status not 500"},"termId":"100071012","termName":"Fall 2021","termNumber":"2021F","termStatus":"A","termOpen":true,"rentalReturnDate":{"year":2021,"month":11,"dayOfMonth":18,"hourOfDay":0,"minute":0,"second":0},"programId":"669","programName":"American University","campusId":"1006","campusName":"American University","institutionName":"American University                                         ","ddcsBreadCrumb":"American University : Fall 2021 : CORE : 100 : 111","adoptionStatus":"100","division":"","divisionName":" ","divisionDescriptorCode":"","department":"CORE","departmentName":"CORE","departmentDescriptorCode":"CORE","course":"100","courseName":"100","courseDescriptorCode":"100","section":"111","sectionName":"111","sectionDescriptorCode":"111","courseId":"81735071","displayFlag":true,"salesTrack":"B","courseMinimum":0,"includEdDTO":{"isStoreIncludEDAllStudents":true,"isIncludEDCampus":false,"isIncludEDSection":false,"isIncludEDTitle":false},"instructor":"Jonathan Miller","sectionAdoptionDTO":{"courseMaterialRelationship":{},"materialAdoptions":{}},"rentalReturnDateDisplay":"12/18/21"},{"courseSectionStatus":{"status":"FAIL","code":"700","description":"Adoption Status not 500"},"termId":"100071012","termName":"Fall 2021","termNumber":"2021F","termStatus":"A","termOpen":true,"rentalReturnDate":{"year":2021,"month":11,"dayOfMonth":18,"hourOfDay":0,"minute":0,"second":0},"programId":"669","programName":"American University","campusId":"1006","campusName":"American University","institutionName":"American University                                         ","ddcsBreadCrumb":"American University : Fall 2021 : CORE : 100 : 112","adoptionStatus":"100","division":"","divisionName":" ","divisionDescriptorCode":"","department":"CORE","departmentName":"CORE","departmentDescriptorCode":"CORE","course":"100","courseName":"100","courseDescriptorCode":"100","section":"112","sectionName":"112","sectionDescriptorCode":"112","courseId":"81735046","displayFlag":true,"salesTrack":"B","courseMinimum":0,"includEdDTO":{"isStoreIncludEDAllStudents":true,"isIncludEDCampus":false,"isIncludEDSection":false,"isIncludEDTitle":false},"instructor":"Jonathan Miller","sectionAdoptionDTO":{"courseMaterialRelationship":{},"materialAdoptions":{}},"rentalReturnDateDisplay":"12/18/21"},{"courseSectionStatus":{"status":"FAIL","code":"700","description":"Adoption Status not 500"},"termId":"100071012","termName":"Fall 2021","termNumber":"2021F","termStatus":"A","termOpen":true,"rentalReturnDate":{"year":2021,"month":11,"dayOfMonth":18,"hourOfDay":0,"minute":0,"second":0},"programId":"669","programName":"American University","campusId":"1006","campusName":"American University","institutionName":"American University                                         ","ddcsBreadCrumb":"American University : Fall 2021 : CORE : 100 : 113","adoptionStatus":"100","division":"","divisionName":" ","divisionDescriptorCode":"","department":"CORE","departmentName":"CORE","departmentDescriptorCode":"CORE","course":"100","courseName":"100","courseDescriptorCode":"100","section":"113","sectionName":"113","sectionDescriptorCode":"113","courseId":"81735105","displayFlag":true,"salesTrack":"B","courseMinimum":0,"includEdDTO":{"isStoreIncludEDAllStudents":true,"isIncludEDCampus":false,"isIncludEDSection":false,"isIncludEDTitle":false},"instructor":"Spencer Bonahoom","sectionAdoptionDTO":{"courseMaterialRelationship":{},"materialAdoptions":{}},"rentalReturnDateDisplay":"12/18/21"},{"courseSectionStatus":{"status":"FAIL","code":"700","description":"Adoption Status not 500"},"termId":"100071012","termName":"Fall 2021","termNumber":"2021F","termStatus":"A","termOpen":true,"rentalReturnDate":{"year":2021,"month":11,"dayOfMonth":18,"hourOfDay":0,"minute":0,"second":0},"programId":"669","programName":"American University","campusId":"1006","campusName":"American University","institutionName":"American University                                         ","ddcsBreadCrumb":"American University : Fall 2021 : CORE : 100 : 114","adoptionStatus":"100","division":"","divisionName":" ","divisionDescriptorCode":"","department":"CORE","departmentName":"CORE","departmentDescriptorCode":"CORE","course":"100","courseName":"100","courseDescriptorCode":"100","section":"114","sectionName":"114","sectionDescriptorCode":"114","courseId":"81735100","displayFlag":true,"salesTrack":"B","courseMinimum":0,"includEdDTO":{"isStoreIncludEDAllStudents":true,"isIncludEDCampus":false,"isIncludEDSection":false,"isIncludEDTitle":false},"instructor":"","sectionAdoptionDTO":{"courseMaterialRelationship":{},"materialAdoptions":{}},"rentalReturnDateDisplay":"12/18/21"},{"courseSectionStatus":{"status":"FAIL","code":"700","description":"Adoption Status not 500"},"termId":"100071012","termName":"Fall 2021","termNumber":"2021F","termStatus":"A","termOpen":true,"rentalReturnDate":{"year":2021,"month":11,"dayOfMonth":18,"hourOfDay":0,"minute":0,"second":0},"programId":"669","programName":"American University","campusId":"1006","campusName":"American University","institutionName":"American University                                         ","ddcsBreadCrumb":"American University : Fall 2021 : CORE : 100 : 115","adoptionStatus":"100","division":"","divisionName":" ","divisionDescriptorCode":"","department":"CORE","departmentName":"CORE","departmentDescriptorCode":"CORE","course":"100","courseName":"100","courseDescriptorCode":"100","section":"115","sectionName":"115","sectionDescriptorCode":"115","courseId":"81735096","displayFlag":true,"salesTrack":"B","courseMinimum":0,"includEdDTO":{"isStoreIncludEDAllStudents":true,"isIncludEDCampus":false,"isIncludEDSection":false,"isIncludEDTitle":false},"instructor":"","sectionAdoptionDTO":{"courseMaterialRelationship":{},"materialAdoptions":{}},"rentalReturnDateDisplay":"12/18/21"},{"courseSectionStatus":{"status":"FAIL","code":"700","description":"Adoption Status not 500"},"termId":"100071012","termName":"Fall 2021","termNumber":"2021F","termStatus":"A","termOpen":true,"rentalReturnDate":{"year":2021,"month":11,"dayOfMonth":18,"hourOfDay":0,"minute":0,"second":0},"programId":"669","programName":"American University","campusId":"1006","campusName":"American University","institutionName":"American University                                         ","ddcsBreadCrumb":"American University : Fall 2021 : CORE : 100 : 116","adoptionStatus":"100","division":"","divisionName":" ","divisionDescriptorCode":"","department":"CORE","departmentName":"CORE","departmentDescriptorCode":"CORE","course":"100","courseName":"100","courseDescriptorCode":"100","section":"116","sectionName":"116","sectionDescriptorCode":"116","courseId":"81735079","displayFlag":true,"salesTrack":"B","courseMinimum":0,"includEdDTO":{"isStoreIncludEDAllStudents":true,"isIncludEDCampus":false,"isIncludEDSection":false,"isIncludEDTitle":false},"instructor":"","sectionAdoptionDTO":{"courseMaterialRelationship":{},"materialAdoptions":{}},"rentalReturnDateDisplay":"12/18/21"},{"courseSectionStatus":{"status":"FAIL","code":"700","description":"Adoption Status not 500"},"termId":"100071012","termName":"Fall 2021","termNumber":"2021F","termStatus":"A","termOpen":true,"rentalReturnDate":{"year":2021,"month":11,"dayOfMonth":18,"hourOfDay":0,"minute":0,"second":0},"programId":"669","programName":"American University","campusId":"1006","campusName":"American University","institutionName":"American University                                         ","ddcsBreadCrumb":"American University : Fall 2021 : CORE : 100 : 117","adoptionStatus":"100","division":"","divisionName":" ","divisionDescriptorCode":"","department":"CORE","departmentName":"CORE","departmentDescriptorCode":"CORE","course":"100","courseName":"100","courseDescriptorCode":"100","section":"117","sectionName":"117","sectionDescriptorCode":"117","courseId":"81735092","displayFlag":true,"salesTrack":"B","courseMinimum":0,"includEdDTO":{"isStoreIncludEDAllStudents":true,"isIncludEDCampus":false,"isIncludEDSection":false,"isIncludEDTitle":false},"instructor":"","sectionAdoptionDTO":{"courseMaterialRelationship":{},"materialAdoptions":{}},"rentalReturnDateDisplay":"12/18/21"},{"courseSectionStatus":{"status":"FAIL","code":"700","description":"Adoption Status not 500"},"termId":"100071012","termName":"Fall 2021","termNumber":"2021F","termStatus":"A","termOpen":true,"rentalReturnDate":{"year":2021,"month":11,"dayOfMonth":18,"hourOfDay":0,"minute":0,"second":0},"programId":"669","programName":"American University","campusId":"1006","campusName":"American University","institutionName":"American University                                         ","ddcsBreadCrumb":"American University : Fall 2021 : CORE : 100 : 118","adoptionStatus":"100","division":"","divisionName":" ","divisionDescriptorCode":"","department":"CORE","departmentName":"CORE","departmentDescriptorCode":"CORE","course":"100","courseName":"100","courseDescriptorCode":"100","section":"118","sectionName":"118","sectionDescriptorCode":"118","courseId":"81735091","displayFlag":true,"salesTrack":"B","courseMinimum":0,"includEdDTO":{"isStoreIncludEDAllStudents":true,"isIncludEDCampus":false,"isIncludEDSection":false,"isIncludEDTitle":false},"instructor":"","sectionAdoptionDTO":{"courseMaterialRelationship":{},"materialAdoptions":{}},"rentalReturnDateDisplay":"12/18/21"},{"courseSectionStatus":{"status":"FAIL","code":"700","description":"Adoption Status not 500"},"termId":"100071012","termName":"Fall 2021","termNumber":"2021F","termStatus":"A","termOpen":true,"rentalReturnDate":{"year":2021,"month":11,"dayOfMonth":18,"hourOfDay":0,"minute":0,"second":0},"programId":"669","programName":"American University","campusId":"1006","campusName":"American University","institutionName":"American University                                         ","ddcsBreadCrumb":"American University : Fall 2021 : CORE : 100 : 119","adoptionStatus":"100","division":"","divisionName":" ","divisionDescriptorCode":"","department":"CORE","departmentName":"CORE","departmentDescriptorCode":"CORE","course":"100","courseName":"100","courseDescriptorCode":"100","section":"119","sectionName":"119","sectionDescriptorCode":"119","courseId":"81735066","displayFlag":true,"salesTrack":"B","courseMinimum":0,"includEdDTO":{"isStoreIncludEDAllStudents":true,"isIncludEDCampus":false,"isIncludEDSection":false,"isIncludEDTitle":false},"instructor":"","sectionAdoptionDTO":{"courseMaterialRelationship":{},"materialAdoptions":{}},"rentalReturnDateDisplay":"12/18/21"},{"courseSectionStatus":{"status":"FAIL","code":"700","description":"Adoption Status not 500"},"termId":"100071012","termName":"Fall 2021","termNumber":"2021F","termStatus":"A","termOpen":true,"rentalReturnDate":{"year":2021,"month":11,"dayOfMonth":18,"hourOfDay":0,"minute":0,"second":0},"programId":"669","programName":"American University","campusId":"1006","campusName":"American University","institutionName":"American University                                         ","ddcsBreadCrumb":"American University : Fall 2021 : CORE : 100 : 120","adoptionStatus":"100","division":"","divisionName":" ","divisionDescriptorCode":"","department":"CORE","departmentName":"CORE","departmentDescriptorCode":"CORE","course":"100","courseName":"100","courseDescriptorCode":"100","section":"120","sectionName":"120","sectionDescriptorCode":"120","courseId":"81735095","displayFlag":true,"salesTrack":"B","courseMinimum":0,"includEdDTO":{"isStoreIncludEDAllStudents":true,"isIncludEDCampus":false,"isIncludEDSection":false,"isIncludEDTitle":false},"instructor":"","sectionAdoptionDTO":{"courseMaterialRelationship":{},"materialAdoptions":{}},"rentalReturnDateDisplay":"12/18/21"},{"courseSectionStatus":{"status":"FAIL","code":"700","description":"Adoption Status not 500"},"termId":"100071012","termName":"Fall 2021","termNumber":"2021F","termStatus":"A","termOpen":true,"rentalReturnDate":{"year":2021,"month":11,"dayOfMonth":18,"hourOfDay":0,"minute":0,"second":0},"programId":"669","programName":"American University","campusId":"1006","campusName":"American University","institutionName":"American University                                         ","ddcsBreadCrumb":"American University : Fall 2021 : CORE : 100 : 121","adoptionStatus":"100","division":"","divisionName":" ","divisionDescriptorCode":"","department":"CORE","departmentName":"CORE","departmentDescriptorCode":"CORE","course":"100","courseName":"100","courseDescriptorCode":"100","section":"121","sectionName":"121","sectionDescriptorCode":"121","courseId":"81735082","displayFlag":true,"salesTrack":"B","courseMinimum":0,"includEdDTO":{"isStoreIncludEDAllStudents":true,"isIncludEDCampus":false,"isIncludEDSection":false,"isIncludEDTitle":false},"instructor":"","sectionAdoptionDTO":{"courseMaterialRelationship":{},"materialAdoptions":{}},"rentalReturnDateDisplay":"12/18/21"},{"courseSectionStatus":{"status":"FAIL","code":"700","description":"Adoption Status not 500"},"termId":"100071012","termName":"Fall 2021","termNumber":"2021F","termStatus":"A","termOpen":true,"rentalReturnDate":{"year":2021,"month":11,"dayOfMonth":18,"hourOfDay":0,"minute":0,"second":0},"programId":"669","programName":"American University","campusId":"1006","campusName":"American University","institutionName":"American University                                         ","ddcsBreadCrumb":"American University : Fall 2021 : CORE : 100 : 122","adoptionStatus":"100","division":"","divisionName":" ","divisionDescriptorCode":"","department":"CORE","departmentName":"CORE","departmentDescriptorCode":"CORE","course":"100","courseName":"100","courseDescriptorCode":"100","section":"122","sectionName":"122","sectionDescriptorCode":"122","courseId":"81735076","displayFlag":true,"salesTrack":"B","courseMinimum":0,"includEdDTO":{"isStoreIncludEDAllStudents":true,"isIncludEDCampus":false,"isIncludEDSection":false,"isIncludEDTitle":false},"instructor":"","sectionAdoptionDTO":{"courseMaterialRelationship":{},"materialAdoptions":{}},"rentalReturnDateDisplay":"12/18/21"},{"courseSectionStatus":{"status":"FAIL","code":"700","description":"Adoption Status not 500"},"termId":"100071012","termName":"Fall 2021","termNumber":"2021F","termStatus":"A","termOpen":true,"rentalReturnDate":{"year":2021,"month":11,"dayOfMonth":18,"hourOfDay":0,"minute":0,"second":0},"programId":"669","programName":"American University","campusId":"1006","campusName":"American University","institutionName":"American University                                         ","ddcsBreadCrumb":"American University : Fall 2021 : CORE : 100 : 123","adoptionStatus":"100","division":"","divisionName":" ","divisionDescriptorCode":"","department":"CORE","departmentName":"CORE","departmentDescriptorCode":"CORE","course":"100","courseName":"100","courseDescriptorCode":"100","section":"123","sectionName":"123","sectionDescriptorCode":"123","courseId":"81735110","displayFlag":true,"salesTrack":"B","courseMinimum":0,"includEdDTO":{"isStoreIncludEDAllStudents":true,"isIncludEDCampus":false,"isIncludEDSection":false,"isIncludEDTitle":false},"instructor":"","sectionAdoptionDTO":{"courseMaterialRelationship":{},"materialAdoptions":{}},"rentalReturnDateDisplay":"12/18/21"},{"courseSectionStatus":{"status":"FAIL","code":"700","description":"Adoption Status not 500"},"termId":"100071012","termName":"Fall 2021","termNumber":"2021F","termStatus":"A","termOpen":true,"rentalReturnDate":{"year":2021,"month":11,"dayOfMonth":18,"hourOfDay":0,"minute":0,"second":0},"programId":"669","programName":"American University","campusId":"1006","campusName":"American University","institutionName":"American University                                         ","ddcsBreadCrumb":"American University : Fall 2021 : CORE : 100 : 124","adoptionStatus":"100","division":"","divisionName":" ","divisionDescriptorCode":"","department":"CORE","departmentName":"CORE","departmentDescriptorCode":"CORE","course":"100","courseName":"100","courseDescriptorCode":"100","section":"124","sectionName":"124","sectionDescriptorCode":"124","courseId":"81735062","displayFlag":true,"salesTrack":"B","courseMinimum":0,"includEdDTO":{"isStoreIncludEDAllStudents":true,"isIncludEDCampus":false,"isIncludEDSection":false,"isIncludEDTitle":false},"instructor":"","sectionAdoptionDTO":{"courseMaterialRelationship":{},"materialAdoptions":{}},"rentalReturnDateDisplay":"12/18/21"},{"courseSectionStatus":{"status":"FAIL","code":"700","description":"Adoption Status not 500"},"termId":"100071012","termName":"Fall 2021","termNumber":"2021F","termStatus":"A","termOpen":true,"rentalReturnDate":{"year":2021,"month":11,"dayOfMonth":18,"hourOfDay":0,"minute":0,"second":0},"programId":"669","programName":"American University","campusId":"1006","campusName":"American University","institutionName":"American University                                         ","ddcsBreadCrumb":"American University : Fall 2021 : CORE : 100 : 125","adoptionStatus":"100","division":"","divisionName":" ","divisionDescriptorCode":"","department":"CORE","departmentName":"CORE","departmentDescriptorCode":"CORE","course":"100","courseName":"100","courseDescriptorCode":"100","section":"125","sectionName":"125","sectionDescriptorCode":"125","courseId":"81735065","displayFlag":true,"salesTrack":"B","courseMinimum":0,"includEdDTO":{"isStoreIncludEDAllStudents":true,"isIncludEDCampus":false,"isIncludEDSection":false,"isIncludEDTitle":false},"instructor":"","sectionAdoptionDTO":{"courseMaterialRelationship":{},"materialAdoptions":{}},"rentalReturnDateDisplay":"12/18/21"},{"courseSectionStatus":{"status":"FAIL","code":"700","description":"Adoption Status not 500"},"termId":"100071012","termName":"Fall 2021","termNumber":"2021F","termStatus":"A","termOpen":true,"rentalReturnDate":{"year":2021,"month":11,"dayOfMonth":18,"hourOfDay":0,"minute":0,"second":0},"programId":"669","programName":"American University","campusId":"1006","campusName":"American University","institutionName":"American University                                         ","ddcsBreadCrumb":"American University : Fall 2021 : CORE : 100 : 126","adoptionStatus":"100","division":"","divisionName":" ","divisionDescriptorCode":"","department":"CORE","departmentName":"CORE","departmentDescriptorCode":"CORE","course":"100","courseName":"100","courseDescriptorCode":"100","section":"126","sectionName":"126","sectionDescriptorCode":"126","courseId":"81735055","displayFlag":true,"salesTrack":"B","courseMinimum":0,"includEdDTO":{"isStoreIncludEDAllStudents":true,"isIncludEDCampus":false,"isIncludEDSection":false,"isIncludEDTitle":false},"instructor":"","sectionAdoptionDTO":{"courseMaterialRelationship":{},"materialAdoptions":{}},"rentalReturnDateDisplay":"12/18/21"},{"courseSectionStatus":{"status":"FAIL","code":"700","description":"Adoption Status not 500"},"termId":"100071012","termName":"Fall 2021","termNumber":"2021F","termStatus":"A","termOpen":true,"rentalReturnDate":{"year":2021,"month":11,"dayOfMonth":18,"hourOfDay":0,"minute":0,"second":0},"programId":"669","programName":"American University","campusId":"1006","campusName":"American University","institutionName":"American University                                         ","ddcsBreadCrumb":"American University : Fall 2021 : CORE : 100 : 127","adoptionStatus":"100","division":"","divisionName":" ","divisionDescriptorCode":"","department":"CORE","departmentName":"CORE","departmentDescriptorCode":"CORE","course":"100","courseName":"100","courseDescriptorCode":"100","section":"127","sectionName":"127","sectionDescriptorCode":"127","courseId":"81735067","displayFlag":true,"salesTrack":"B","courseMinimum":0,"includEdDTO":{"isStoreIncludEDAllStudents":true,"isIncludEDCampus":false,"isIncludEDSection":false,"isIncludEDTitle":false},"instructor":"","sectionAdoptionDTO":{"courseMaterialRelationship":{},"materialAdoptions":{}},"rentalReturnDateDisplay":"12/18/21"},{"courseSectionStatus":{"status":"FAIL","code":"700","description":"Adoption Status not 500"},"termId":"100071012","termName":"Fall 2021","termNumber":"2021F","termStatus":"A","termOpen":true,"rentalReturnDate":{"year":2021,"month":11,"dayOfMonth":18,"hourOfDay":0,"minute":0,"second":0},"programId":"669","programName":"American University","campusId":"1006","campusName":"American University","institutionName":"American University                                         ","ddcsBreadCrumb":"American University : Fall 2021 : CORE : 100 : 128","adoptionStatus":"100","division":"","divisionName":" ","divisionDescriptorCode":"","department":"CORE","departmentName":"CORE","departmentDescriptorCode":"CORE","course":"100","courseName":"100","courseDescriptorCode":"100","section":"128","sectionName":"128","sectionDescriptorCode":"128","courseId":"81735088","displayFlag":true,"salesTrack":"B","courseMinimum":0,"includEdDTO":{"isStoreIncludEDAllStudents":true,"isIncludEDCampus":false,"isIncludEDSection":false,"isIncludEDTitle":false},"instructor":"","sectionAdoptionDTO":{"courseMaterialRelationship":{},"materialAdoptions":{}},"rentalReturnDateDisplay":"12/18/21"},{"courseSectionStatus":{"status":"FAIL","code":"700","description":"Adoption Status not 500"},"termId":"100071012","termName":"Fall 2021","termNumber":"2021F","termStatus":"A","termOpen":true,"rentalReturnDate":{"year":2021,"month":11,"dayOfMonth":18,"hourOfDay":0,"minute":0,"second":0},"programId":"669","programName":"American University","campusId":"1006","campusName":"American University","institutionName":"American University                                         ","ddcsBreadCrumb":"American University : Fall 2021 : CORE : 100 : 129","adoptionStatus":"100","division":"","divisionName":" ","divisionDescriptorCode":"","department":"CORE","departmentName":"CORE","departmentDescriptorCode":"CORE","course":"100","courseName":"100","courseDescriptorCode":"100","section":"129","sectionName":"129","sectionDescriptorCode":"129","courseId":"81735051","displayFlag":true,"salesTrack":"B","courseMinimum":0,"includEdDTO":{"isStoreIncludEDAllStudents":true,"isIncludEDCampus":false,"isIncludEDSection":false,"isIncludEDTitle":false},"instructor":"","sectionAdoptionDTO":{"courseMaterialRelationship":{},"materialAdoptions":{}},"rentalReturnDateDisplay":"12/18/21"},{"courseSectionStatus":{"status":"FAIL","code":"700","description":"Adoption Status not 500"},"termId":"100071012","termName":"Fall 2021","termNumber":"2021F","termStatus":"A","termOpen":true,"rentalReturnDate":{"year":2021,"month":11,"dayOfMonth":18,"hourOfDay":0,"minute":0,"second":0},"programId":"669","programName":"American University","campusId":"1006","campusName":"American University","institutionName":"American University                                         ","ddcsBreadCrumb":"American University : Fall 2021 : CORE : 100 : 130","adoptionStatus":"100","division":"","divisionName":" ","divisionDescriptorCode":"","department":"CORE","departmentName":"CORE","departmentDescriptorCode":"CORE","course":"100","courseName":"100","courseDescriptorCode":"100","section":"130","sectionName":"130","sectionDescriptorCode":"130","courseId":"81735072","displayFlag":true,"salesTrack":"B","courseMinimum":0,"includEdDTO":{"isStoreIncludEDAllStudents":true,"isIncludEDCampus":false,"isIncludEDSection":false,"isIncludEDTitle":false},"instructor":"","sectionAdoptionDTO":{"courseMaterialRelationship":{},"materialAdoptions":{}},"rentalReturnDateDisplay":"12/18/21"}],"statusDTO":{"status":"SUCCESS","code":"0"},"homePageURL":"/Home/11077-10061-1?demoKey=d","searchLimit":0,"DDCSBrowseRetentionLevel":"TERM","accordionControl":"ALL_CLOSED","ddcsNotesControl":"NOTES_CLOSED","digitalSurChargeFee":"3.99","summaryProfile":false}]